[{"Pattern": "Marubozu White", "From": "20220131 0", "To": "20220131 0"}, {"Pattern": "Marubozu White", "From": "20220209 0", "To": "20220209 0"}, {"Pattern": "Hammer", "From": "20220413 0", "To": "20220413 0"}, {"Pattern": "Marubozu White", "From": "20220517 0", "To": "20220517 0"}, {"Pattern": "Hammer", "From": "20220614 0", "To": "20220614 0"}, {"Pattern": "Marubozu Black", "From": "20220801 0", "To": "20220801 0"}, {"Pattern": "Marubozu Black", "From": "20220805 0", "To": "20220805 0"}, {"Pattern": "Marubozu White", "From": "20220823 0", "To": "20220823 0"}, {"Pattern": "Marubozu White", "From": "20220909 0", "To": "20220909 0"}, {"Pattern": "Piercing Pattern", "From": "20221007 0", "To": "20221010 0"}, {"Pattern": "Marubozu Black", "From": "20221208 0", "To": "20221208 0"}, {"Pattern": "Marubozu White", "From": "20221220 0", "To": "20221220 0"}, {"Pattern": "Marubozu White", "From": "20230111 0", "To": "20230111 0"}, {"Pattern": "Marubozu White", "From": "20230131 0", "To": "20230131 0"}]